{
	"configurations" : 
	[
		{
			"directories" : 
			[
				{
					"build" : ".",
					"jsonFile" : "directory-.-Debug-f5ebdc15457944623624.json",
					"minimumCMakeVersion" : 
					{
						"string" : "3.5"
					},
					"projectIndex" : 0,
					"source" : ".",
					"targetIndexes" : 
					[
						0
					]
				}
			],
			"name" : "Debug",
			"projects" : 
			[
				{
					"directoryIndexes" : 
					[
						0
					],
					"name" : "AutoMake",
					"targetIndexes" : 
					[
						0
					]
				}
			],
			"targets" : 
			[
				{
					"directoryIndex" : 0,
					"id" : "AutoMake::@6890427a1f51a3e7e1df",
					"jsonFile" : "target-AutoMake-Debug-8fe512e3fcc8987aa34d.json",
					"name" : "AutoMake",
					"projectIndex" : 0
				}
			]
		}
	],
	"kind" : "codemodel",
	"paths" : 
	{
		"build" : "/home/ice/lab/automake/build-AutoMake-Desktop_Qt_6_2_2_GCC_64bit-Debug",
		"source" : "/home/ice/lab/automake/AutoMake"
	},
	"version" : 
	{
		"major" : 2,
		"minor" : 3
	}
}
